{
   "POST session/09807558-5edc-4106-9ba3-6b77b59219d5/element $VAR1 = {'using' => 'id','value' => 'metainput'};" : [
      "HTTP/1.1 200 OK\nCache-Control: no-cache\nCache-Control: no-cache\nConnection: close\nDate: Sun, 19 Oct 2014 21:42:16 GMT\nServer: Jetty/5.1.x (Mac OS X/10.10 x86_64 java/1.8.0\nContent-Length: 170\nContent-Type: application/json; charset=utf-8\nExpires: Thu, 01 Jan 1970 00:00:00 GMT\nExpires: Thu, 01 Jan 1970 00:00:00 GMT\nClient-Date: Sun, 19 Oct 2014 21:42:16 GMT\nClient-Peer: 127.0.0.1:4444\nClient-Response-Num: 1\n\n{\"state\":\"success\",\"sessionId\":\"09807558-5edc-4106-9ba3-6b77b59219d5\",\"hCode\":1831202287,\"value\":{\"ELEMENT\":\"5\"},\"class\":\"org.openqa.selenium.remote.Response\",\"status\":0}\n"
   ],
   "POST session/09807558-5edc-4106-9ba3-6b77b59219d5/element $VAR1 = {'using' => 'xpath','value' => '//a[@href=\\'/index.html\\']'};" : [
      "HTTP/1.1 200 OK\nCache-Control: no-cache\nCache-Control: no-cache\nConnection: close\nDate: Sun, 19 Oct 2014 21:42:15 GMT\nServer: Jetty/5.1.x (Mac OS X/10.10 x86_64 java/1.8.0\nContent-Length: 169\nContent-Type: application/json; charset=utf-8\nExpires: Thu, 01 Jan 1970 00:00:00 GMT\nExpires: Thu, 01 Jan 1970 00:00:00 GMT\nClient-Date: Sun, 19 Oct 2014 21:42:16 GMT\nClient-Peer: 127.0.0.1:4444\nClient-Response-Num: 1\n\n{\"state\":\"success\",\"sessionId\":\"09807558-5edc-4106-9ba3-6b77b59219d5\",\"hCode\":157140202,\"value\":{\"ELEMENT\":\"0\"},\"class\":\"org.openqa.selenium.remote.Response\",\"status\":0}\n"
   ],
   "POST session/09807558-5edc-4106-9ba3-6b77b59219d5/url $VAR1 = {'url' => 'http://localhost:63636/dragAndDropTest.html'};" : [
      "HTTP/1.1 200 OK\nCache-Control: no-cache\nCache-Control: no-cache\nConnection: close\nDate: Sun, 19 Oct 2014 21:42:16 GMT\nServer: Jetty/5.1.x (Mac OS X/10.10 x86_64 java/1.8.0\nContent-Length: 159\nContent-Type: application/json; charset=utf-8\nExpires: Thu, 01 Jan 1970 00:00:00 GMT\nExpires: Thu, 01 Jan 1970 00:00:00 GMT\nClient-Date: Sun, 19 Oct 2014 21:42:16 GMT\nClient-Peer: 127.0.0.1:4444\nClient-Response-Num: 1\n\n{\"state\":\"success\",\"sessionId\":\"09807558-5edc-4106-9ba3-6b77b59219d5\",\"hCode\":1269749692,\"value\":null,\"class\":\"org.openqa.selenium.remote.Response\",\"status\":0}\n"
   ],
   "DELETE session/09807558-5edc-4106-9ba3-6b77b59219d5 $VAR1 = {};" : [
      "HTTP/1.1 200 OK\nCache-Control: no-cache\nCache-Control: no-cache\nConnection: close\nDate: Sun, 19 Oct 2014 21:42:16 GMT\nServer: Jetty/5.1.x (Mac OS X/10.10 x86_64 java/1.8.0\nContent-Length: 159\nContent-Type: application/json; charset=utf-8\nExpires: Thu, 01 Jan 1970 00:00:00 GMT\nExpires: Thu, 01 Jan 1970 00:00:00 GMT\nClient-Date: Sun, 19 Oct 2014 21:42:16 GMT\nClient-Peer: 127.0.0.1:4444\nClient-Response-Num: 1\n\n{\"state\":\"success\",\"sessionId\":\"09807558-5edc-4106-9ba3-6b77b59219d5\",\"hCode\":1060852687,\"value\":null,\"class\":\"org.openqa.selenium.remote.Response\",\"status\":0}\n"
   ],
   "POST session/09807558-5edc-4106-9ba3-6b77b59219d5/element/4/toggle $VAR1 = {};" : [
      "HTTP/1.1 500 Internal Server Error\nCache-Control: no-cache\nCache-Control: no-cache\nConnection: close\nDate: Sun, 19 Oct 2014 21:42:16 GMT\nServer: Jetty/5.1.x (Mac OS X/10.10 x86_64 java/1.8.0\nContent-Length: 1282\nContent-Type: application/json; charset=utf-8\nExpires: Thu, 01 Jan 1970 00:00:00 GMT\nExpires: Thu, 01 Jan 1970 00:00:00 GMT\nClient-Date: Sun, 19 Oct 2014 21:42:16 GMT\nClient-Peer: 127.0.0.1:4444\nClient-Response-Num: 1\n\n{\"state\":\"unhandled error\",\"sessionId\":null,\"hCode\":593136220,\"value\":{\"additionalInformation\":\"\\nDriver info: driver.version: unknown\",\"localizedMessage\":\"POST /session/09807558-5edc-4106-9ba3-6b77b59219d5/element/4/toggle\\nBuild info: version: '2.43.1', revision: '5163bce', time: '2014-09-10 16:27:33'\\nSystem info: host: 'MBP-de-Emmanuel', ip: '192.168.1.26', os.name: 'Mac OS X', os.arch: 'x86_64', os.version: '10.10', java.version: '1.8.0'\\nDriver info: driver.version: unknown\",\"supportUrl\":null,\"systemInformation\":\"System info: host: 'MBP-de-Emmanuel', ip: '192.168.1.26', os.name: 'Mac OS X', os.arch: 'x86_64', os.version: '10.10', java.version: '1.8.0'\",\"cause\":null,\"stackTrace\":[null,null,null,null,null,null,null,null,null,null,null,null,null,null,null,null,null,null,null],\"suppressed\":[],\"message\":\"POST /session/09807558-5edc-4106-9ba3-6b77b59219d5/element/4/toggle\\nBuild info: version: '2.43.1', revision: '5163bce', time: '2014-09-10 16:27:33'\\nSystem info: host: 'MBP-de-Emmanuel', ip: '192.168.1.26', os.name: 'Mac OS X', os.arch: 'x86_64', os.version: '10.10', java.version: '1.8.0'\\nDriver info: driver.version: unknown\",\"hCode\":337101929,\"class\":\"org.openqa.selenium.UnsupportedCommandException\"},\"class\":\"org.openqa.selenium.remote.Response\",\"status\":13}\n"
   ],
   "POST session/09807558-5edc-4106-9ba3-6b77b59219d5/element/0/click $VAR1 = {};" : [
      "HTTP/1.1 200 OK\nCache-Control: no-cache\nCache-Control: no-cache\nConnection: close\nDate: Sun, 19 Oct 2014 21:42:16 GMT\nServer: Jetty/5.1.x (Mac OS X/10.10 x86_64 java/1.8.0\nContent-Length: 159\nContent-Type: application/json; charset=utf-8\nExpires: Thu, 01 Jan 1970 00:00:00 GMT\nExpires: Thu, 01 Jan 1970 00:00:00 GMT\nClient-Date: Sun, 19 Oct 2014 21:42:16 GMT\nClient-Peer: 127.0.0.1:4444\nClient-Response-Num: 1\n\n{\"state\":\"success\",\"sessionId\":\"09807558-5edc-4106-9ba3-6b77b59219d5\",\"hCode\":1685221035,\"value\":null,\"class\":\"org.openqa.selenium.remote.Response\",\"status\":0}\n"
   ],
   "POST session/09807558-5edc-4106-9ba3-6b77b59219d5/url $VAR1 = {'url' => 'http://localhost:63636/formPage.html'};" : [
      "HTTP/1.1 200 OK\nCache-Control: no-cache\nCache-Control: no-cache\nConnection: close\nDate: Sun, 19 Oct 2014 21:42:15 GMT\nServer: Jetty/5.1.x (Mac OS X/10.10 x86_64 java/1.8.0\nContent-Length: 159\nContent-Type: application/json; charset=utf-8\nExpires: Thu, 01 Jan 1970 00:00:00 GMT\nExpires: Thu, 01 Jan 1970 00:00:00 GMT\nClient-Date: Sun, 19 Oct 2014 21:42:15 GMT\nClient-Peer: 127.0.0.1:4444\nClient-Response-Num: 1\n\n{\"state\":\"success\",\"sessionId\":\"09807558-5edc-4106-9ba3-6b77b59219d5\",\"hCode\":1474775999,\"value\":null,\"class\":\"org.openqa.selenium.remote.Response\",\"status\":0}\n"
   ],
   "POST session/09807558-5edc-4106-9ba3-6b77b59219d5/element $VAR1 = {'using' => 'id','value' => 'checky'};" : [
      "HTTP/1.1 200 OK\nCache-Control: no-cache\nCache-Control: no-cache\nConnection: close\nDate: Sun, 19 Oct 2014 21:42:16 GMT\nServer: Jetty/5.1.x (Mac OS X/10.10 x86_64 java/1.8.0\nContent-Length: 170\nContent-Type: application/json; charset=utf-8\nExpires: Thu, 01 Jan 1970 00:00:00 GMT\nExpires: Thu, 01 Jan 1970 00:00:00 GMT\nClient-Date: Sun, 19 Oct 2014 21:42:16 GMT\nClient-Peer: 127.0.0.1:4444\nClient-Response-Num: 1\n\n{\"state\":\"success\",\"sessionId\":\"09807558-5edc-4106-9ba3-6b77b59219d5\",\"hCode\":2123325009,\"value\":{\"ELEMENT\":\"4\"},\"class\":\"org.openqa.selenium.remote.Response\",\"status\":0}\n"
   ],
   "POST session $VAR1 = {'desiredCapabilities' => {'acceptSslCerts' => bless( do{\\(my $o = 1)}, 'JSON::PP::Boolean' ),'browserName' => 'firefox','javascriptEnabled' => $VAR1->{'desiredCapabilities'}{'acceptSslCerts'},'platform' => 'ANY','version' => ''}};" : [
      "HTTP/1.1 200 OK\nCache-Control: no-cache\nCache-Control: no-cache\nConnection: close\nDate: Sun, 19 Oct 2014 21:42:14 GMT\nServer: Jetty/5.1.x (Mac OS X/10.10 x86_64 java/1.8.0\nContent-Length: 543\nContent-Type: application/json; charset=utf-8\nExpires: Thu, 01 Jan 1970 00:00:00 GMT\nExpires: Thu, 01 Jan 1970 00:00:00 GMT\nClient-Date: Sun, 19 Oct 2014 21:42:15 GMT\nClient-Peer: 127.0.0.1:4444\nClient-Response-Num: 1\n\n{\"state\":null,\"sessionId\":\"09807558-5edc-4106-9ba3-6b77b59219d5\",\"hCode\":2066192883,\"value\":{\"applicationCacheEnabled\":true,\"rotatable\":false,\"handlesAlerts\":true,\"databaseEnabled\":true,\"version\":\"33.0\",\"platform\":\"MAC\",\"nativeEvents\":false,\"acceptSslCerts\":true,\"webdriver.remote.sessionid\":\"09807558-5edc-4106-9ba3-6b77b59219d5\",\"webStorageEnabled\":true,\"locationContextEnabled\":true,\"browserName\":\"firefox\",\"takesScreenshot\":true,\"javascriptEnabled\":true,\"cssSelectorsEnabled\":true},\"class\":\"org.openqa.selenium.remote.Response\",\"status\":0}\n"
   ],
   "GET session/09807558-5edc-4106-9ba3-6b77b59219d5/element/3/attribute/missing-attribute $VAR1 = {};" : [
      "HTTP/1.1 200 OK\nCache-Control: no-cache\nCache-Control: no-cache\nConnection: close\nDate: Sun, 19 Oct 2014 21:42:16 GMT\nServer: Jetty/5.1.x (Mac OS X/10.10 x86_64 java/1.8.0\nContent-Length: 159\nContent-Type: application/json; charset=utf-8\nExpires: Thu, 01 Jan 1970 00:00:00 GMT\nExpires: Thu, 01 Jan 1970 00:00:00 GMT\nClient-Date: Sun, 19 Oct 2014 21:42:16 GMT\nClient-Peer: 127.0.0.1:4444\nClient-Response-Num: 1\n\n{\"state\":\"success\",\"sessionId\":\"09807558-5edc-4106-9ba3-6b77b59219d5\",\"hCode\":1240512073,\"value\":null,\"class\":\"org.openqa.selenium.remote.Response\",\"status\":0}\n"
   ],
   "GET session/09807558-5edc-4106-9ba3-6b77b59219d5/element/3/name $VAR1 = {};" : [
      "HTTP/1.1 200 OK\nCache-Control: no-cache\nCache-Control: no-cache\nConnection: close\nDate: Sun, 19 Oct 2014 21:42:16 GMT\nServer: Jetty/5.1.x (Mac OS X/10.10 x86_64 java/1.8.0\nContent-Length: 161\nContent-Type: application/json; charset=utf-8\nExpires: Thu, 01 Jan 1970 00:00:00 GMT\nExpires: Thu, 01 Jan 1970 00:00:00 GMT\nClient-Date: Sun, 19 Oct 2014 21:42:16 GMT\nClient-Peer: 127.0.0.1:4444\nClient-Response-Num: 1\n\n{\"state\":\"success\",\"sessionId\":\"09807558-5edc-4106-9ba3-6b77b59219d5\",\"hCode\":687122373,\"value\":\"input\",\"class\":\"org.openqa.selenium.remote.Response\",\"status\":0}\n"
   ],
   "GET session/09807558-5edc-4106-9ba3-6b77b59219d5/element/2/text $VAR1 = {};" : [
      "HTTP/1.1 200 OK\nCache-Control: no-cache\nCache-Control: no-cache\nConnection: close\nDate: Sun, 19 Oct 2014 21:42:16 GMT\nServer: Jetty/5.1.x (Mac OS X/10.10 x86_64 java/1.8.0\nContent-Length: 168\nContent-Type: application/json; charset=utf-8\nExpires: Thu, 01 Jan 1970 00:00:00 GMT\nExpires: Thu, 01 Jan 1970 00:00:00 GMT\nClient-Date: Sun, 19 Oct 2014 21:42:16 GMT\nClient-Peer: 127.0.0.1:4444\nClient-Response-Num: 1\n\n{\"state\":\"success\",\"sessionId\":\"09807558-5edc-4106-9ba3-6b77b59219d5\",\"hCode\":296451720,\"value\":\"Example text\",\"class\":\"org.openqa.selenium.remote.Response\",\"status\":0}\n"
   ],
   "GET session/09807558-5edc-4106-9ba3-6b77b59219d5/element/8/displayed $VAR1 = {};" : [
      "HTTP/1.1 200 OK\nCache-Control: no-cache\nCache-Control: no-cache\nConnection: close\nDate: Sun, 19 Oct 2014 21:42:16 GMT\nServer: Jetty/5.1.x (Mac OS X/10.10 x86_64 java/1.8.0\nContent-Length: 160\nContent-Type: application/json; charset=utf-8\nExpires: Thu, 01 Jan 1970 00:00:00 GMT\nExpires: Thu, 01 Jan 1970 00:00:00 GMT\nClient-Date: Sun, 19 Oct 2014 21:42:16 GMT\nClient-Peer: 127.0.0.1:4444\nClient-Response-Num: 1\n\n{\"state\":\"success\",\"sessionId\":\"09807558-5edc-4106-9ba3-6b77b59219d5\",\"hCode\":1372291673,\"value\":false,\"class\":\"org.openqa.selenium.remote.Response\",\"status\":0}\n",
      "HTTP/1.1 200 OK\nCache-Control: no-cache\nCache-Control: no-cache\nConnection: close\nDate: Sun, 19 Oct 2014 21:42:16 GMT\nServer: Jetty/5.1.x (Mac OS X/10.10 x86_64 java/1.8.0\nContent-Length: 159\nContent-Type: application/json; charset=utf-8\nExpires: Thu, 01 Jan 1970 00:00:00 GMT\nExpires: Thu, 01 Jan 1970 00:00:00 GMT\nClient-Date: Sun, 19 Oct 2014 21:42:16 GMT\nClient-Peer: 127.0.0.1:4444\nClient-Response-Num: 1\n\n{\"state\":\"success\",\"sessionId\":\"09807558-5edc-4106-9ba3-6b77b59219d5\",\"hCode\":966940802,\"value\":false,\"class\":\"org.openqa.selenium.remote.Response\",\"status\":0}\n"
   ],
   "GET session/09807558-5edc-4106-9ba3-6b77b59219d5/element/7/displayed $VAR1 = {};" : [
      "HTTP/1.1 200 OK\nCache-Control: no-cache\nCache-Control: no-cache\nConnection: close\nDate: Sun, 19 Oct 2014 21:42:16 GMT\nServer: Jetty/5.1.x (Mac OS X/10.10 x86_64 java/1.8.0\nContent-Length: 158\nContent-Type: application/json; charset=utf-8\nExpires: Thu, 01 Jan 1970 00:00:00 GMT\nExpires: Thu, 01 Jan 1970 00:00:00 GMT\nClient-Date: Sun, 19 Oct 2014 21:42:16 GMT\nClient-Peer: 127.0.0.1:4444\nClient-Response-Num: 1\n\n{\"state\":\"success\",\"sessionId\":\"09807558-5edc-4106-9ba3-6b77b59219d5\",\"hCode\":172775843,\"value\":true,\"class\":\"org.openqa.selenium.remote.Response\",\"status\":0}\n",
      "HTTP/1.1 200 OK\nCache-Control: no-cache\nCache-Control: no-cache\nConnection: close\nDate: Sun, 19 Oct 2014 21:42:16 GMT\nServer: Jetty/5.1.x (Mac OS X/10.10 x86_64 java/1.8.0\nContent-Length: 156\nContent-Type: application/json; charset=utf-8\nExpires: Thu, 01 Jan 1970 00:00:00 GMT\nExpires: Thu, 01 Jan 1970 00:00:00 GMT\nClient-Date: Sun, 19 Oct 2014 21:42:16 GMT\nClient-Peer: 127.0.0.1:4444\nClient-Response-Num: 1\n\n{\"state\":\"success\",\"sessionId\":\"09807558-5edc-4106-9ba3-6b77b59219d5\",\"hCode\":8438762,\"value\":true,\"class\":\"org.openqa.selenium.remote.Response\",\"status\":0}\n"
   ],
   "POST session/09807558-5edc-4106-9ba3-6b77b59219d5/element $VAR1 = {'using' => 'id','value' => 'id-name1'};" : [
      "HTTP/1.1 200 OK\nCache-Control: no-cache\nCache-Control: no-cache\nConnection: close\nDate: Sun, 19 Oct 2014 21:42:16 GMT\nServer: Jetty/5.1.x (Mac OS X/10.10 x86_64 java/1.8.0\nContent-Length: 169\nContent-Type: application/json; charset=utf-8\nExpires: Thu, 01 Jan 1970 00:00:00 GMT\nExpires: Thu, 01 Jan 1970 00:00:00 GMT\nClient-Date: Sun, 19 Oct 2014 21:42:16 GMT\nClient-Peer: 127.0.0.1:4444\nClient-Response-Num: 1\n\n{\"state\":\"success\",\"sessionId\":\"09807558-5edc-4106-9ba3-6b77b59219d5\",\"hCode\":419676908,\"value\":{\"ELEMENT\":\"3\"},\"class\":\"org.openqa.selenium.remote.Response\",\"status\":0}\n"
   ],
   "POST session/09807558-5edc-4106-9ba3-6b77b59219d5/element/4/click $VAR1 = {};" : [
      "HTTP/1.1 200 OK\nCache-Control: no-cache\nCache-Control: no-cache\nConnection: close\nDate: Sun, 19 Oct 2014 21:42:16 GMT\nServer: Jetty/5.1.x (Mac OS X/10.10 x86_64 java/1.8.0\nContent-Length: 158\nContent-Type: application/json; charset=utf-8\nExpires: Thu, 01 Jan 1970 00:00:00 GMT\nExpires: Thu, 01 Jan 1970 00:00:00 GMT\nClient-Date: Sun, 19 Oct 2014 21:42:16 GMT\nClient-Peer: 127.0.0.1:4444\nClient-Response-Num: 1\n\n{\"state\":\"success\",\"sessionId\":\"09807558-5edc-4106-9ba3-6b77b59219d5\",\"hCode\":452336694,\"value\":null,\"class\":\"org.openqa.selenium.remote.Response\",\"status\":0}\n"
   ],
   "GET session/09807558-5edc-4106-9ba3-6b77b59219d5/element/6/location $VAR1 = {};" : [
      "HTTP/1.1 200 OK\nCache-Control: no-cache\nCache-Control: no-cache\nConnection: close\nDate: Sun, 19 Oct 2014 21:42:16 GMT\nServer: Jetty/5.1.x (Mac OS X/10.10 x86_64 java/1.8.0\nContent-Length: 220\nContent-Type: application/json; charset=utf-8\nExpires: Thu, 01 Jan 1970 00:00:00 GMT\nExpires: Thu, 01 Jan 1970 00:00:00 GMT\nClient-Date: Sun, 19 Oct 2014 21:42:16 GMT\nClient-Peer: 127.0.0.1:4444\nClient-Response-Num: 1\n\n{\"state\":\"success\",\"sessionId\":\"09807558-5edc-4106-9ba3-6b77b59219d5\",\"hCode\":1519849742,\"value\":{\"x\":8,\"y\":8,\"hCode\":8388608,\"class\":\"org.openqa.selenium.Point\"},\"class\":\"org.openqa.selenium.remote.Response\",\"status\":0}\n",
      "HTTP/1.1 200 OK\nCache-Control: no-cache\nCache-Control: no-cache\nConnection: close\nDate: Sun, 19 Oct 2014 21:42:16 GMT\nServer: Jetty/5.1.x (Mac OS X/10.10 x86_64 java/1.8.0\nContent-Length: 219\nContent-Type: application/json; charset=utf-8\nExpires: Thu, 01 Jan 1970 00:00:00 GMT\nExpires: Thu, 01 Jan 1970 00:00:00 GMT\nClient-Date: Sun, 19 Oct 2014 21:42:16 GMT\nClient-Peer: 127.0.0.1:4444\nClient-Response-Num: 1\n\n{\"state\":\"success\",\"sessionId\":\"09807558-5edc-4106-9ba3-6b77b59219d5\",\"hCode\":675560151,\"value\":{\"x\":8,\"y\":8,\"hCode\":8388608,\"class\":\"org.openqa.selenium.Point\"},\"class\":\"org.openqa.selenium.remote.Response\",\"status\":0}\n"
   ],
   "GET session/09807558-5edc-4106-9ba3-6b77b59219d5/element/3/attribute/value $VAR1 = {};" : [
      "HTTP/1.1 200 OK\nCache-Control: no-cache\nCache-Control: no-cache\nConnection: close\nDate: Sun, 19 Oct 2014 21:42:16 GMT\nServer: Jetty/5.1.x (Mac OS X/10.10 x86_64 java/1.8.0\nContent-Length: 158\nContent-Type: application/json; charset=utf-8\nExpires: Thu, 01 Jan 1970 00:00:00 GMT\nExpires: Thu, 01 Jan 1970 00:00:00 GMT\nClient-Date: Sun, 19 Oct 2014 21:42:16 GMT\nClient-Peer: 127.0.0.1:4444\nClient-Response-Num: 1\n\n{\"state\":\"success\",\"sessionId\":\"09807558-5edc-4106-9ba3-6b77b59219d5\",\"hCode\":926461994,\"value\":\"id\",\"class\":\"org.openqa.selenium.remote.Response\",\"status\":0}\n",
      "HTTP/1.1 200 OK\nCache-Control: no-cache\nCache-Control: no-cache\nConnection: close\nDate: Sun, 19 Oct 2014 21:42:16 GMT\nServer: Jetty/5.1.x (Mac OS X/10.10 x86_64 java/1.8.0\nContent-Length: 159\nContent-Type: application/json; charset=utf-8\nExpires: Thu, 01 Jan 1970 00:00:00 GMT\nExpires: Thu, 01 Jan 1970 00:00:00 GMT\nClient-Date: Sun, 19 Oct 2014 21:42:16 GMT\nClient-Peer: 127.0.0.1:4444\nClient-Response-Num: 1\n\n{\"state\":\"success\",\"sessionId\":\"09807558-5edc-4106-9ba3-6b77b59219d5\",\"hCode\":1315117515,\"value\":\"id\",\"class\":\"org.openqa.selenium.remote.Response\",\"status\":0}\n"
   ],
   "POST session/09807558-5edc-4106-9ba3-6b77b59219d5/element $VAR1 = {'using' => 'id','value' => 'withText'};" : [
      "HTTP/1.1 200 OK\nCache-Control: no-cache\nCache-Control: no-cache\nConnection: close\nDate: Sun, 19 Oct 2014 21:42:16 GMT\nServer: Jetty/5.1.x (Mac OS X/10.10 x86_64 java/1.8.0\nContent-Length: 170\nContent-Type: application/json; charset=utf-8\nExpires: Thu, 01 Jan 1970 00:00:00 GMT\nExpires: Thu, 01 Jan 1970 00:00:00 GMT\nClient-Date: Sun, 19 Oct 2014 21:42:16 GMT\nClient-Peer: 127.0.0.1:4444\nClient-Response-Num: 1\n\n{\"state\":\"success\",\"sessionId\":\"09807558-5edc-4106-9ba3-6b77b59219d5\",\"hCode\":1592219040,\"value\":{\"ELEMENT\":\"2\"},\"class\":\"org.openqa.selenium.remote.Response\",\"status\":0}\n"
   ],
   "POST session/09807558-5edc-4106-9ba3-6b77b59219d5/url $VAR1 = {'url' => 'http://localhost:63636/index.html'};" : [
      "HTTP/1.1 200 OK\nCache-Control: no-cache\nCache-Control: no-cache\nConnection: close\nDate: Sun, 19 Oct 2014 21:42:16 GMT\nServer: Jetty/5.1.x (Mac OS X/10.10 x86_64 java/1.8.0\nContent-Length: 159\nContent-Type: application/json; charset=utf-8\nExpires: Thu, 01 Jan 1970 00:00:00 GMT\nExpires: Thu, 01 Jan 1970 00:00:00 GMT\nClient-Date: Sun, 19 Oct 2014 21:42:16 GMT\nClient-Peer: 127.0.0.1:4444\nClient-Response-Num: 1\n\n{\"state\":\"success\",\"sessionId\":\"09807558-5edc-4106-9ba3-6b77b59219d5\",\"hCode\":1332258253,\"value\":null,\"class\":\"org.openqa.selenium.remote.Response\",\"status\":0}\n"
   ],
   "POST session/09807558-5edc-4106-9ba3-6b77b59219d5/modifier $VAR1 = {'isdown' => 1,'value' => 'Alt'};" : [
      "HTTP/1.1 500 Internal Server Error\nCache-Control: no-cache\nCache-Control: no-cache\nConnection: close\nDate: Sun, 19 Oct 2014 21:42:16 GMT\nServer: Jetty/5.1.x (Mac OS X/10.10 x86_64 java/1.8.0\nContent-Length: 1268\nContent-Type: application/json; charset=utf-8\nExpires: Thu, 01 Jan 1970 00:00:00 GMT\nExpires: Thu, 01 Jan 1970 00:00:00 GMT\nClient-Date: Sun, 19 Oct 2014 21:42:16 GMT\nClient-Peer: 127.0.0.1:4444\nClient-Response-Num: 1\n\n{\"state\":\"unhandled error\",\"sessionId\":null,\"hCode\":1203460270,\"value\":{\"additionalInformation\":\"\\nDriver info: driver.version: unknown\",\"localizedMessage\":\"POST /session/09807558-5edc-4106-9ba3-6b77b59219d5/modifier\\nBuild info: version: '2.43.1', revision: '5163bce', time: '2014-09-10 16:27:33'\\nSystem info: host: 'MBP-de-Emmanuel', ip: '192.168.1.26', os.name: 'Mac OS X', os.arch: 'x86_64', os.version: '10.10', java.version: '1.8.0'\\nDriver info: driver.version: unknown\",\"supportUrl\":null,\"systemInformation\":\"System info: host: 'MBP-de-Emmanuel', ip: '192.168.1.26', os.name: 'Mac OS X', os.arch: 'x86_64', os.version: '10.10', java.version: '1.8.0'\",\"cause\":null,\"stackTrace\":[null,null,null,null,null,null,null,null,null,null,null,null,null,null,null,null,null,null,null],\"suppressed\":[],\"message\":\"POST /session/09807558-5edc-4106-9ba3-6b77b59219d5/modifier\\nBuild info: version: '2.43.1', revision: '5163bce', time: '2014-09-10 16:27:33'\\nSystem info: host: 'MBP-de-Emmanuel', ip: '192.168.1.26', os.name: 'Mac OS X', os.arch: 'x86_64', os.version: '10.10', java.version: '1.8.0'\\nDriver info: driver.version: unknown\",\"hCode\":1432615155,\"class\":\"org.openqa.selenium.UnsupportedCommandException\"},\"class\":\"org.openqa.selenium.remote.Response\",\"status\":13}\n"
   ],
   "POST session/09807558-5edc-4106-9ba3-6b77b59219d5/element $VAR1 = {'using' => 'id','value' => 'displayed'};" : [
      "HTTP/1.1 200 OK\nCache-Control: no-cache\nCache-Control: no-cache\nConnection: close\nDate: Sun, 19 Oct 2014 21:42:16 GMT\nServer: Jetty/5.1.x (Mac OS X/10.10 x86_64 java/1.8.0\nContent-Length: 168\nContent-Type: application/json; charset=utf-8\nExpires: Thu, 01 Jan 1970 00:00:00 GMT\nExpires: Thu, 01 Jan 1970 00:00:00 GMT\nClient-Date: Sun, 19 Oct 2014 21:42:16 GMT\nClient-Peer: 127.0.0.1:4444\nClient-Response-Num: 1\n\n{\"state\":\"success\",\"sessionId\":\"09807558-5edc-4106-9ba3-6b77b59219d5\",\"hCode\":56835508,\"value\":{\"ELEMENT\":\"7\"},\"class\":\"org.openqa.selenium.remote.Response\",\"status\":0}\n"
   ],
   "GET session/09807558-5edc-4106-9ba3-6b77b59219d5/element/6/size $VAR1 = {};" : [
      "HTTP/1.1 200 OK\nCache-Control: no-cache\nCache-Control: no-cache\nConnection: close\nDate: Sun, 19 Oct 2014 21:42:16 GMT\nServer: Jetty/5.1.x (Mac OS X/10.10 x86_64 java/1.8.0\nContent-Length: 239\nContent-Type: application/json; charset=utf-8\nExpires: Thu, 01 Jan 1970 00:00:00 GMT\nExpires: Thu, 01 Jan 1970 00:00:00 GMT\nClient-Date: Sun, 19 Oct 2014 21:42:16 GMT\nClient-Peer: 127.0.0.1:4444\nClient-Response-Num: 1\n\n{\"state\":\"success\",\"sessionId\":\"09807558-5edc-4106-9ba3-6b77b59219d5\",\"hCode\":1588297738,\"value\":{\"width\":18,\"hCode\":-2147483648,\"class\":\"org.openqa.selenium.Dimension\",\"height\":18},\"class\":\"org.openqa.selenium.remote.Response\",\"status\":0}\n"
   ],
   "GET session/09807558-5edc-4106-9ba3-6b77b59219d5/title $VAR1 = {};" : [
      "HTTP/1.1 200 OK\nCache-Control: no-cache\nCache-Control: no-cache\nConnection: close\nDate: Sun, 19 Oct 2014 21:42:16 GMT\nServer: Jetty/5.1.x (Mac OS X/10.10 x86_64 java/1.8.0\nContent-Length: 172\nContent-Type: application/json; charset=utf-8\nExpires: Thu, 01 Jan 1970 00:00:00 GMT\nExpires: Thu, 01 Jan 1970 00:00:00 GMT\nClient-Date: Sun, 19 Oct 2014 21:42:16 GMT\nClient-Peer: 127.0.0.1:4444\nClient-Response-Num: 1\n\n{\"state\":\"success\",\"sessionId\":\"09807558-5edc-4106-9ba3-6b77b59219d5\",\"hCode\":1317701280,\"value\":\"Hello WebDriver\",\"class\":\"org.openqa.selenium.remote.Response\",\"status\":0}\n"
   ],
   "POST session/09807558-5edc-4106-9ba3-6b77b59219d5/element/active $VAR1 = {};" : [
      "HTTP/1.1 200 OK\nCache-Control: no-cache\nCache-Control: no-cache\nConnection: close\nDate: Sun, 19 Oct 2014 21:42:16 GMT\nServer: Jetty/5.1.x (Mac OS X/10.10 x86_64 java/1.8.0\nContent-Length: 169\nContent-Type: application/json; charset=utf-8\nExpires: Thu, 01 Jan 1970 00:00:00 GMT\nExpires: Thu, 01 Jan 1970 00:00:00 GMT\nClient-Date: Sun, 19 Oct 2014 21:42:16 GMT\nClient-Peer: 127.0.0.1:4444\nClient-Response-Num: 1\n\n{\"state\":\"success\",\"sessionId\":\"09807558-5edc-4106-9ba3-6b77b59219d5\",\"hCode\":601725911,\"value\":{\"ELEMENT\":\"1\"},\"class\":\"org.openqa.selenium.remote.Response\",\"status\":0}\n"
   ],
   "POST session/09807558-5edc-4106-9ba3-6b77b59219d5/element/6/drag $VAR1 = {'x' => 200,'y' => 200};" : [
      "HTTP/1.1 500 Internal Server Error\nCache-Control: no-cache\nCache-Control: no-cache\nConnection: close\nDate: Sun, 19 Oct 2014 21:42:16 GMT\nServer: Jetty/5.1.x (Mac OS X/10.10 x86_64 java/1.8.0\nContent-Length: 1280\nContent-Type: application/json; charset=utf-8\nExpires: Thu, 01 Jan 1970 00:00:00 GMT\nExpires: Thu, 01 Jan 1970 00:00:00 GMT\nClient-Date: Sun, 19 Oct 2014 21:42:16 GMT\nClient-Peer: 127.0.0.1:4444\nClient-Response-Num: 1\n\n{\"state\":\"unhandled error\",\"sessionId\":null,\"hCode\":1683763459,\"value\":{\"additionalInformation\":\"\\nDriver info: driver.version: unknown\",\"localizedMessage\":\"POST /session/09807558-5edc-4106-9ba3-6b77b59219d5/element/6/drag\\nBuild info: version: '2.43.1', revision: '5163bce', time: '2014-09-10 16:27:33'\\nSystem info: host: 'MBP-de-Emmanuel', ip: '192.168.1.26', os.name: 'Mac OS X', os.arch: 'x86_64', os.version: '10.10', java.version: '1.8.0'\\nDriver info: driver.version: unknown\",\"supportUrl\":null,\"systemInformation\":\"System info: host: 'MBP-de-Emmanuel', ip: '192.168.1.26', os.name: 'Mac OS X', os.arch: 'x86_64', os.version: '10.10', java.version: '1.8.0'\",\"cause\":null,\"stackTrace\":[null,null,null,null,null,null,null,null,null,null,null,null,null,null,null,null,null,null,null],\"suppressed\":[],\"message\":\"POST /session/09807558-5edc-4106-9ba3-6b77b59219d5/element/6/drag\\nBuild info: version: '2.43.1', revision: '5163bce', time: '2014-09-10 16:27:33'\\nSystem info: host: 'MBP-de-Emmanuel', ip: '192.168.1.26', os.name: 'Mac OS X', os.arch: 'x86_64', os.version: '10.10', java.version: '1.8.0'\\nDriver info: driver.version: unknown\",\"hCode\":1727354450,\"class\":\"org.openqa.selenium.UnsupportedCommandException\"},\"class\":\"org.openqa.selenium.remote.Response\",\"status\":13}\n"
   ],
   "GET session/09807558-5edc-4106-9ba3-6b77b59219d5/element/4/selected $VAR1 = {};" : [
      "HTTP/1.1 200 OK\nCache-Control: no-cache\nCache-Control: no-cache\nConnection: close\nDate: Sun, 19 Oct 2014 21:42:16 GMT\nServer: Jetty/5.1.x (Mac OS X/10.10 x86_64 java/1.8.0\nContent-Length: 159\nContent-Type: application/json; charset=utf-8\nExpires: Thu, 01 Jan 1970 00:00:00 GMT\nExpires: Thu, 01 Jan 1970 00:00:00 GMT\nClient-Date: Sun, 19 Oct 2014 21:42:16 GMT\nClient-Peer: 127.0.0.1:4444\nClient-Response-Num: 1\n\n{\"state\":\"success\",\"sessionId\":\"09807558-5edc-4106-9ba3-6b77b59219d5\",\"hCode\":389106586,\"value\":false,\"class\":\"org.openqa.selenium.remote.Response\",\"status\":0}\n",
      "HTTP/1.1 200 OK\nCache-Control: no-cache\nCache-Control: no-cache\nConnection: close\nDate: Sun, 19 Oct 2014 21:42:16 GMT\nServer: Jetty/5.1.x (Mac OS X/10.10 x86_64 java/1.8.0\nContent-Length: 158\nContent-Type: application/json; charset=utf-8\nExpires: Thu, 01 Jan 1970 00:00:00 GMT\nExpires: Thu, 01 Jan 1970 00:00:00 GMT\nClient-Date: Sun, 19 Oct 2014 21:42:16 GMT\nClient-Peer: 127.0.0.1:4444\nClient-Response-Num: 1\n\n{\"state\":\"success\",\"sessionId\":\"09807558-5edc-4106-9ba3-6b77b59219d5\",\"hCode\":512730351,\"value\":true,\"class\":\"org.openqa.selenium.remote.Response\",\"status\":0}\n",
      "HTTP/1.1 200 OK\nCache-Control: no-cache\nCache-Control: no-cache\nConnection: close\nDate: Sun, 19 Oct 2014 21:42:16 GMT\nServer: Jetty/5.1.x (Mac OS X/10.10 x86_64 java/1.8.0\nContent-Length: 159\nContent-Type: application/json; charset=utf-8\nExpires: Thu, 01 Jan 1970 00:00:00 GMT\nExpires: Thu, 01 Jan 1970 00:00:00 GMT\nClient-Date: Sun, 19 Oct 2014 21:42:16 GMT\nClient-Peer: 127.0.0.1:4444\nClient-Response-Num: 1\n\n{\"state\":\"success\",\"sessionId\":\"09807558-5edc-4106-9ba3-6b77b59219d5\",\"hCode\":2002563800,\"value\":true,\"class\":\"org.openqa.selenium.remote.Response\",\"status\":0}\n"
   ],
   "POST session/09807558-5edc-4106-9ba3-6b77b59219d5/element $VAR1 = {'using' => 'id','value' => 'hidden'};" : [
      "HTTP/1.1 200 OK\nCache-Control: no-cache\nCache-Control: no-cache\nConnection: close\nDate: Sun, 19 Oct 2014 21:42:16 GMT\nServer: Jetty/5.1.x (Mac OS X/10.10 x86_64 java/1.8.0\nContent-Length: 169\nContent-Type: application/json; charset=utf-8\nExpires: Thu, 01 Jan 1970 00:00:00 GMT\nExpires: Thu, 01 Jan 1970 00:00:00 GMT\nClient-Date: Sun, 19 Oct 2014 21:42:16 GMT\nClient-Peer: 127.0.0.1:4444\nClient-Response-Num: 1\n\n{\"state\":\"success\",\"sessionId\":\"09807558-5edc-4106-9ba3-6b77b59219d5\",\"hCode\":445960403,\"value\":{\"ELEMENT\":\"8\"},\"class\":\"org.openqa.selenium.remote.Response\",\"status\":0}\n"
   ],
   "POST session/09807558-5edc-4106-9ba3-6b77b59219d5/back $VAR1 = {};" : [
      "HTTP/1.1 200 OK\nCache-Control: no-cache\nCache-Control: no-cache\nConnection: close\nDate: Sun, 19 Oct 2014 21:42:16 GMT\nServer: Jetty/5.1.x (Mac OS X/10.10 x86_64 java/1.8.0\nContent-Length: 158\nContent-Type: application/json; charset=utf-8\nExpires: Thu, 01 Jan 1970 00:00:00 GMT\nExpires: Thu, 01 Jan 1970 00:00:00 GMT\nClient-Date: Sun, 19 Oct 2014 21:42:16 GMT\nClient-Peer: 127.0.0.1:4444\nClient-Response-Num: 1\n\n{\"state\":\"success\",\"sessionId\":\"09807558-5edc-4106-9ba3-6b77b59219d5\",\"hCode\":697786639,\"value\":null,\"class\":\"org.openqa.selenium.remote.Response\",\"status\":0}\n"
   ],
   "POST session/09807558-5edc-4106-9ba3-6b77b59219d5/url $VAR1 = {'url' => 'http://localhost:63636/metakeys.html'};" : [
      "HTTP/1.1 200 OK\nCache-Control: no-cache\nCache-Control: no-cache\nConnection: close\nDate: Sun, 19 Oct 2014 21:42:16 GMT\nServer: Jetty/5.1.x (Mac OS X/10.10 x86_64 java/1.8.0\nContent-Length: 157\nContent-Type: application/json; charset=utf-8\nExpires: Thu, 01 Jan 1970 00:00:00 GMT\nExpires: Thu, 01 Jan 1970 00:00:00 GMT\nClient-Date: Sun, 19 Oct 2014 21:42:16 GMT\nClient-Peer: 127.0.0.1:4444\nClient-Response-Num: 1\n\n{\"state\":\"success\",\"sessionId\":\"09807558-5edc-4106-9ba3-6b77b59219d5\",\"hCode\":10735109,\"value\":null,\"class\":\"org.openqa.selenium.remote.Response\",\"status\":0}\n"
   ],
   "POST session/09807558-5edc-4106-9ba3-6b77b59219d5/element $VAR1 = {'using' => 'id','value' => 'test1'};" : [
      "HTTP/1.1 200 OK\nCache-Control: no-cache\nCache-Control: no-cache\nConnection: close\nDate: Sun, 19 Oct 2014 21:42:16 GMT\nServer: Jetty/5.1.x (Mac OS X/10.10 x86_64 java/1.8.0\nContent-Length: 169\nContent-Type: application/json; charset=utf-8\nExpires: Thu, 01 Jan 1970 00:00:00 GMT\nExpires: Thu, 01 Jan 1970 00:00:00 GMT\nClient-Date: Sun, 19 Oct 2014 21:42:16 GMT\nClient-Peer: 127.0.0.1:4444\nClient-Response-Num: 1\n\n{\"state\":\"success\",\"sessionId\":\"09807558-5edc-4106-9ba3-6b77b59219d5\",\"hCode\":161878451,\"value\":{\"ELEMENT\":\"6\"},\"class\":\"org.openqa.selenium.remote.Response\",\"status\":0}\n"
   ]
}
